aigist/__init__.py
aigist/main.py
aigist/app/__init__.py
aigist/app/database.py
aigist/app/lite_llm.py
aigist/app/models.py
aigist/app/services.py
app/__init__.py
app/database.py
app/lite_llm.py
app/models.py
app/services.py
aigist-0.0.3.dist-info/LICENSE
aigist-0.0.3.dist-info/METADATA
aigist-0.0.3.dist-info/WHEEL
aigist-0.0.3.dist-info/entry_points.txt
aigist-0.0.3.dist-info/top_level.txt
aigist-0.0.3.dist-info/RECORD
