Metadata-Version: 2.1
Name: aigist
Version: 0.0.3
Summary: This project provides a FastAPI application to create and update GitHub gists using the GitHub API. It includes SQLite for persistence and is designed to run in a GitHub Codespace.
Home-page: 
Author: rUv
Author-email: 
License: Apache License 2.0
Classifier: Development Status :: 3 - Alpha
Classifier: Intended Audience :: Developers
Classifier: Topic :: Software Development :: Libraries :: Application Frameworks
Classifier: License :: OSI Approved :: Apache Software License
Classifier: Programming Language :: Python :: 3
Classifier: Programming Language :: Python :: 3.7
Classifier: Programming Language :: Python :: 3.8
Classifier: Programming Language :: Python :: 3.9
Classifier: Programming Language :: Python :: 3.10
License-File: LICENSE
Requires-Dist: twine
Requires-Dist: setuptools
Requires-Dist: wheel
Requires-Dist: flake8
Requires-Dist: black
Requires-Dist: pytest
Requires-Dist: pip-upgrader
